{
  "id" : "EB02-030",
  "rarity" : "C",
  "name" : "And That's When Somebody Makes Fun of Their Friend's Dream!!!!",
  "category" : "EVENT",
  "cost" : 2,
  "attribute" : "",
  "power" : null,
  "counter" : null,
  "color" : "Blue",
  "blockIcon" : 3,
  "type" : "Alabasta/Straw Hat Crew",
  "effect" : "[Counter] If any of your Characters would be K.O.'d in battle during this turn, you may trash 1 card from your hand instead.",
  "trigger" : "[Trigger] Draw 1 card.",
  "keywords" : [ "Counter" ]
}