{
  "id" : "OP15-060",
  "rarity" : "SR",
  "name" : "Enel",
  "category" : "CHARACTER",
  "cost" : 6,
  "attribute" : "Special",
  "power" : 8000,
  "counter" : null,
  "color" : "Purple",
  "blockIcon" : 4,
  "type" : "Sky Island",
  "effect" : "If you have 6 or less DON!! cards on your field, this Character cannot be removed from the field by your opponent's effects and gains +2000 power. [Activate: Main] DON!! −1: This Character gains [Blocker] until the end of your opponent's next End Phase. Then, trash 1 card from your hand.",
  "trigger" : "",
  "keywords" : [ "Blocker", "Activate: Main" ]
}