{
  "id" : "OP06-062",
  "rarity" : "SR",
  "name" : "Vinsmoke Judge",
  "category" : "CHARACTER",
  "cost" : 8,
  "attribute" : "Slash",
  "power" : 8000,
  "counter" : null,
  "color" : "Purple",
  "blockIcon" : 2,
  "type" : "The Vinsmoke Family/GERMA 66",
  "effect" : "[On Play] DON!! −1 (You may return the specified number of DON!! cards from your field to your DON!! deck.) You may trash 2 cards from your hand: Play up to 4 {GERMA 66} type Character cards with different card names and 4000 power or less from your trash. [Activate: Main] [Once Per Turn] DON!! −1: Rest up to 1 of your opponent's DON!! cards.",
  "trigger" : "",
  "keywords" : [ "On Play", "Activate: Main" ]
}